LICENSE
README.md
setup.cfg
setup.py
webmo/__init__.py
webmo/gui.py
webmo/spectrum.py
webmo/util.py
webmo/webmo_rest.py
webmo.egg-info/PKG-INFO
webmo.egg-info/SOURCES.txt
webmo.egg-info/dependency_links.txt
webmo.egg-info/requires.txt
webmo.egg-info/top_level.txt