Metadata-Version: 2.1
Name: webmo
Version: 1.4.1
Summary: A Python-based interface to WebMO
Home-page: https://github.com/jrschmidt2/webmo-python
Download-URL: https://github.com/jrschmidt2/webmo-python/archive/refs/tags/1.4.1.tar.gz
Author: J.R. Schmidt
Author-email: schmidt@webmo.net
License: MIT
Keywords: WEBMO,REST,API
Provides-Extra: spectrum
Provides-Extra: util
Provides-Extra: gui
Provides-Extra: all
License-File: LICENSE
